{
  "id": 293,
  "url": "/release/293/",
  "title": "モーニング娘。ライブ初の武道館〜ダンシング ラブ サイト 2000 春〜",
  "category": "DVD",
  "artist": "モーニング娘。",
  "releaseDate": "2000.8.29",
  "label": "zetima",
  "images": [
    "/upload/images/cb7fad25302158d2af0703cb91752e4c82b2fbb7.webp"
  ],
  "editions": [
    {
      "name": null,
      "image": null,
      "price": null,
      "discs": [
        {
          "type": "DVD",
          "tracks": [
            {
              "index": 1,
              "title": "OPENING",
              "duration": "05:22",
              "credits": {
                "出演": "モーニング娘。"
              }
            },
            {
              "index": 2,
              "title": "ハッピーサマーウェディング",
              "duration": "05:01",
              "credits": {
                "作詞": "つんく",
                "作曲": "つんく",
                "編曲": "ダンス☆マン(horn arrangement by 川松久芳",
                "出演": "モーニング娘。"
              }
            },
            {
              "index": 3,
              "title": "恋のダンスサイト",
              "duration": "04:29",
              "credits": {
                "作詞": "つんく",
                "作曲": "つんく",
                "編曲": "ダンス☆マン",
                "出演": "モーニング娘。"
              }
            },
            {
              "index": 4,
              "title": "愛車 ローンで",
              "duration": "05:00",
              "credits": {
                "作詞": "つんく",
                "作曲": "つんく",
                "編曲": "小西貴雄",
                "出演": "モーニング娘。"
              }
            },
            {
              "index": 5,
              "title": "MC",
              "duration": "06:53",
              "credits": {
                "出演": "モーニング娘。"
              }
            },
            {
              "index": 6,
              "title": "真夏の光線",
              "duration": "05:50",
              "credits": {
                "作詞": "つんく",
                "作曲": "つんく",
                "編曲": "河野 伸",
                "出演": "モーニング娘。"
              }
            },
            {
              "index": 7,
              "title": "おもいで",
              "duration": "04:40",
              "credits": {
                "作詞": "つんく",
                "作曲": "つんく",
                "編曲": "鈴木俊介",
                "出演": "モーニング娘。"
              }
            },
            {
              "index": 8,
              "title": "DANCEするのだ！",
              "duration": "05:05",
              "credits": {
                "作詞": "つんく",
                "作曲": "つんく",
                "編曲": "ダンス☆マン",
                "出演": "モーニング娘。"
              }
            },
            {
              "index": 9,
              "title": "北海道シャララ",
              "duration": "03:33",
              "credits": {
                "作詞": "まこと＆つんく",
                "作曲": "つんく",
                "編曲": "高橋諭一",
                "出演": "カントリー娘。"
              }
            },
            {
              "index": 10,
              "title": "告白記念日",
              "duration": "03:25",
              "credits": {
                "作詞": "つんく",
                "作曲": "つんく",
                "編曲": "河野 伸",
                "出演": "メロン記念日"
              }
            },
            {
              "index": 11,
              "title": "捨てないでよ",
              "duration": "03:03",
              "credits": {
                "作詞": "つんく",
                "作曲": "つんく",
                "編曲": "川口 真",
                "出演": "中澤ゆうこ"
              }
            },
            {
              "index": 12,
              "title": "たんぽぽ",
              "duration": "03:47",
              "credits": {
                "作詞": "つんく",
                "作曲": "つんく",
                "編曲": "小西貴雄",
                "出演": "タンポポ"
              }
            },
            {
              "index": 13,
              "title": "ちょこっとLOVE",
              "duration": "04:15",
              "credits": {
                "作詞": "つんく",
                "作曲": "つんく",
                "編曲": "松原 憲",
                "出演": "プッチモニ"
              }
            },
            {
              "index": 13,
              "title": "MC",
              "duration": "00:45",
              "credits": {
                "出演": "モーニング娘。"
              }
            },
            {
              "index": 14,
              "title": "原宿6:00集合",
              "duration": "03:50",
              "credits": {
                "作詞": "つんく",
                "作曲": "つんく",
                "編曲": "山内 薫",
                "出演": "モーニング娘。"
              }
            },
            {
              "index": 15,
              "title": "未来の扉",
              "duration": "04:09",
              "credits": {
                "作詞": "つんく",
                "作曲": "つんく",
                "編曲": "今井了介",
                "出演": "モーニング娘。"
              }
            },
            {
              "index": 16,
              "title": "抱いて HOLD ON ME!",
              "duration": "04:32",
              "credits": {
                "作詞": "つんく",
                "作曲": "つんく",
                "編曲": "前嶋康明",
                "出演": "モーニング娘。"
              }
            },
            {
              "index": 17,
              "title": "LOVEマシーン",
              "duration": "05:56",
              "credits": {
                "作詞": "つんく",
                "作曲": "つんく",
                "編曲": "ダンス☆マン",
                "出演": "モーニング娘。"
              }
            },
            {
              "index": 18,
              "title": "MC",
              "duration": "09:55",
              "credits": {
                "出演": "モーニング娘。"
              }
            },
            {
              "index": 19,
              "title": "モーニングコーヒー",
              "duration": "04:42",
              "credits": {
                "作詞": "つんく",
                "作曲": "つんく",
                "編曲": "桜井鉄太郎",
                "出演": "モーニング娘。"
              }
            },
            {
              "index": 20,
              "title": "サマーナイトタウン",
              "duration": "04:29",
              "credits": {
                "作詞": "つんく",
                "作曲": "つんく",
                "編曲": "前嶋康明",
                "出演": "モーニング娘。"
              }
            },
            {
              "index": 21,
              "title": "ハッピーサマーウェディング",
              "duration": "02:30",
              "suffix": "ENDING",
              "credits": {
                "作詞": "つんく",
                "作曲": "つんく",
                "編曲": "ダンス☆マン(horn arrangement by 川松久芳)",
                "出演": "モーニング娘。"
              }
            },
            {
              "index": 21,
              "title": "ダディドゥデドダディ！",
              "duration": "06:56",
              "credits": {
                "作詞": "つんく",
                "作曲": "つんく",
                "編曲": "鈴木俊介",
                "出演": "モーニング娘。"
              }
            }
          ],
          "catalogNo": "EPBE-5011"
        }
      ]
    }
  ]
}